<?xml version="1.0" encoding="UTF-8" ?>
<!DOCTYPE mapper PUBLIC "-//mybatis.org//DTD Mapper 3.0//EN" "http://mybatis.org/dtd/mybatis-3-mapper.dtd" >
<mapper namespace="com.jw.sys.dao.NoticeDao" >
  <resultMap id="BaseResultMap" type="com.jw.sys.bean.vo.NoticeVo" >
    <!--
      WARNING - @mbggenerated
      This element is automatically generated by MyBatis Generator, do not modify.
    -->
    <id column="id" property="id" jdbcType="INTEGER" />
    <result column="title" property="title" jdbcType="VARCHAR" />
    <result column="type" property="type" jdbcType="INTEGER" />
    <result column="createtime" property="createtime" jdbcType="DATE" />
    <result column="creater" property="creater" jdbcType="INTEGER" />
  </resultMap>
  <resultMap id="ResultMapWithBLOBs" type="com.jw.sys.bean.entity.Notice" extends="BaseResultMap" >
    <!--
      WARNING - @mbggenerated
      This element is automatically generated by MyBatis Generator, do not modify.
    -->
    <result column="content" property="content" jdbcType="LONGVARCHAR" />
  </resultMap>
  <sql id="Base_Column_List" >
    <!--
      WARNING - @mbggenerated
      This element is automatically generated by MyBatis Generator, do not modify.
    -->
    id, title, type, createtime, creater
  </sql>
  <sql id="Blob_Column_List" >
    <!--
      WARNING - @mbggenerated
      This element is automatically generated by MyBatis Generator, do not modify.
    -->
    content
  </sql>
  <select id="selectById" resultMap="ResultMapWithBLOBs" parameterType="java.lang.Integer" >
    <!--
      WARNING - @mbggenerated
      This element is automatically generated by MyBatis Generator, do not modify.
    -->
    select 
    <include refid="Base_Column_List" />
    ,
    <include refid="Blob_Column_List" />
    from sys_notice
    where id = #{noticeId,jdbcType=INTEGER}
  </select>
  <delete id="deleteById" parameterType="java.lang.Integer" >
    <!--
      WARNING - @mbggenerated
      This element is automatically generated by MyBatis Generator, do not modify.
    -->
    delete from sys_notice
    where id = #{noticeId,jdbcType=INTEGER}
  </delete>
  <insert id="insert" parameterType="com.jw.sys.bean.vo.NoticeVo" >
    <!--
      WARNING - @mbggenerated
      This element is automatically generated by MyBatis Generator, do not modify.
    -->
    <selectKey resultType="java.lang.Integer" keyProperty="id" order="BEFORE" >
      SELECT LAST_INSERT_ID()
    </selectKey>
    insert into sys_notice (id, title, type,
      createtime, creater, content
      )
    values (#{id,jdbcType=INTEGER}, #{title,jdbcType=VARCHAR}, #{type,jdbcType=INTEGER}, 
      #{createtime,jdbcType=TIMESTAMP}, #{creater,jdbcType=INTEGER}, #{content,jdbcType=LONGVARCHAR}
      )
  </insert>
  <insert id="insertSelective" parameterType="com.jw.sys.bean.vo.NoticeVo" >
    <!--
      WARNING - @mbggenerated
      This element is automatically generated by MyBatis Generator, do not modify.
    -->
    <selectKey resultType="java.lang.Integer" keyProperty="id" order="BEFORE" >
      SELECT LAST_INSERT_ID()
    </selectKey>
    insert into sys_notice
    <trim prefix="(" suffix=")" suffixOverrides="," >
      id,
      <if test="title != null" >
        title,
      </if>
      <if test="type != null" >
        type,
      </if>
      <if test="createtime != null" >
        createtime,
      </if>
      <if test="creater != null" >
        creater,
      </if>
      <if test="content != null" >
        content,
      </if>
    </trim>
    <trim prefix="values (" suffix=")" suffixOverrides="," >
      #{id,jdbcType=INTEGER},
      <if test="title != null" >
        #{title,jdbcType=VARCHAR},
      </if>
      <if test="type != null" >
        #{type,jdbcType=INTEGER},
      </if>
      <if test="createtime != null" >
        #{createtime,jdbcType=TIMESTAMP},
      </if>
      <if test="creater != null" >
        #{creater,jdbcType=INTEGER},
      </if>
      <if test="content != null" >
        #{content,jdbcType=LONGVARCHAR},
      </if>
    </trim>
  </insert>
  <update id="updateByPrimaryKeySelective" parameterType="com.jw.sys.bean.vo.NoticeVo" >
    <!--
      WARNING - @mbggenerated
      This element is automatically generated by MyBatis Generator, do not modify.
    -->
    update sys_notice
    <set >
      <if test="title != null" >
        title = #{title,jdbcType=VARCHAR},
      </if>
      <if test="type != null" >
        type = #{type,jdbcType=INTEGER},
      </if>
      <if test="createtime != null" >
        createtime = #{createtime,jdbcType=TIMESTAMP},
      </if>
      <if test="creater != null" >
        creater = #{creater,jdbcType=INTEGER},
      </if>
      <if test="content != null" >
        content = #{content,jdbcType=LONGVARCHAR},
      </if>
    </set>
    where id = #{id,jdbcType=INTEGER}
  </update>
  <update id="updateByPrimaryKeyWithBLOBs" parameterType="com.jw.sys.bean.vo.NoticeVo" >
    <!--
      WARNING - @mbggenerated
      This element is automatically generated by MyBatis Generator, do not modify.
    -->
    update sys_notice
    set title = #{title,jdbcType=VARCHAR},
      type = #{type,jdbcType=INTEGER},
      createtime = #{createtime,jdbcType=TIMESTAMP},
      creater = #{creater,jdbcType=INTEGER},
      content = #{content,jdbcType=LONGVARCHAR}
    where id = #{id,jdbcType=INTEGER}
  </update>
  <update id="updateById" parameterType="java.lang.Integer" >
    <!--
      WARNING - @mbggenerated
      This element is automatically generated by MyBatis Generator, do not modify.
    -->
    update sys_notice
    set title = #{title,jdbcType=VARCHAR},
      type = #{type,jdbcType=INTEGER},
      createtime = #{createtime,jdbcType=TIMESTAMP},
      creater = #{creater,jdbcType=INTEGER}
    where id = #{id,jdbcType=INTEGER}
  </update>
  <select id="list" resultMap="ResultMapWithBLOBs">
    select * from sys_notice
    <if test="condition != null and condition != ''">
      where title like CONCAT('%',#{condition},'%') or content like CONCAT('%',#{condition},'%')
    </if>
    order by createtime DESC
  </select>
  <select id="listAll" resultMap="BaseResultMap">
    select * from sys_notice
    order by createtime DESC
  </select>
</mapper>